lisbet/__init__.py
lisbet/_version.py
lisbet/analysis.py
lisbet/cli.py
lisbet/drawing.py
lisbet/evaluation.py
lisbet/hub.py
lisbet/modeling.py
lisbet/plotting.py
lisbet/postprocessing.py
lisbet/transforms_extra.py
lisbet/unsupervised.py
lisbet/utils.py
lisbet/video.py
lisbet/datasets/__init__.py
lisbet/datasets/common.py
lisbet/datasets/iterable_style.py
lisbet/datasets/map_style.py
lisbet/inference/__init__.py
lisbet/inference/annotation.py
lisbet/inference/common.py
lisbet/inference/embedding.py
lisbet/io/__init__.py
lisbet/io/core.py
lisbet/io/ext_sources/__init__.py
lisbet/io/ext_sources/calms21.py
lisbet/io/ext_sources/mabe22.py
lisbet/training/__init__.py
lisbet/training/core.py
lisbet/training/preprocessing.py
lisbet/training/tasks.py
lisbet/training/utils.py
lisbet-0.3.2.dist-info/licenses/LICENSE
lisbet-0.3.2.dist-info/METADATA
lisbet-0.3.2.dist-info/WHEEL
lisbet-0.3.2.dist-info/entry_points.txt
lisbet-0.3.2.dist-info/top_level.txt
lisbet-0.3.2.dist-info/RECORD
