Metadata-Version: 2.4
Name: lisbet
Version: 0.3.2
Summary: LISBET (LISBET Is a Social BEhavior Transformer)
Author-email: Giuseppe Chindemi <giuseppe.chindemi@unige.ch>, Benoit Girard <benoit.girard@unige.ch>
Requires-Python: >=3.10
License-File: LICENSE
Requires-Dist: h5py
Requires-Dist: hmmlearn
Requires-Dist: huggingface_hub
Requires-Dist: joblib
Requires-Dist: lightning
Requires-Dist: matplotlib
Requires-Dist: movement
Requires-Dist: numpy
Requires-Dist: pandas
Requires-Dist: pooch
Requires-Dist: pyyaml
Requires-Dist: scikit-learn
Requires-Dist: seaborn
Requires-Dist: torch
Requires-Dist: torchinfo
Requires-Dist: torchvision
Requires-Dist: tqdm
Requires-Dist: umap-learn
Requires-Dist: rich
Provides-Extra: docs
Requires-Dist: pydata-sphinx-theme; extra == "docs"
Requires-Dist: sphinx; extra == "docs"
Requires-Dist: sphinx-autodoc-typehints; extra == "docs"
Requires-Dist: sphinx-copybutton; extra == "docs"
Requires-Dist: sphinx-design; extra == "docs"
Requires-Dist: sphinx-gallery; extra == "docs"
Provides-Extra: tests
Requires-Dist: pytest; extra == "tests"
Provides-Extra: dev
Requires-Dist: lisbet[docs,tests]; extra == "dev"
Dynamic: license-file
